mcp_twitter/__init__.py
mcp_twitter/server.py
mcp_twitter-0.0.2.dist-info/METADATA
mcp_twitter-0.0.2.dist-info/WHEEL
mcp_twitter-0.0.2.dist-info/entry_points.txt
mcp_twitter-0.0.2.dist-info/top_level.txt
mcp_twitter-0.0.2.dist-info/RECORD
